gitomator-0.1.3.dist-info/METADATA
gitomator-0.1.3.dist-info/WHEEL
gitomator/py.typed
gitomator/tests/test_basics.py
gitomator/_gitomator.pyi
gitomator/__init__.py
gitomator/__init__.pyi
gitomator/_gitomator.cp312-win_amd64.pyd
gitomator-0.1.3.dist-info/RECORD
