Metadata-Version: 2.4
Name: gitomator
Version: 0.1.3
Classifier: Development Status :: 4 - Beta
Classifier: Intended Audience :: Developers
Classifier: License :: OSI Approved :: MIT License
Classifier: Programming Language :: Python :: 3
Classifier: Programming Language :: Python :: 3.9
Classifier: Programming Language :: Python :: 3.10
Classifier: Programming Language :: Python :: 3.11
Classifier: Programming Language :: Python :: 3.12
Classifier: Topic :: Software Development :: Libraries
Classifier: Topic :: Software Development :: Version Control :: Git
Classifier: Typing :: Typed
Summary: Python package for Git operations
Author: ben <bmeddeb@asu.edu>
Author-email: Ben Meddeb <bmeddeb@asu.edu>
License: MIT
Requires-Python: >=3.9
Project-URL: Repository, https://github.com/bmeddeb/Gitomator
Project-URL: Documentation, https://gitomator.readthedocs.io/
Project-URL: Bug Tracker, https://github.com/bmeddeb/Gitomator/issues
